src/__init__.py
src/strictargs.py
src/rule/__init__.py
src/rule/sa_bool.py
src/rule/sa_float.py
src/rule/sa_int.py
src/rule/sa_string.py
test/__init__.py
test/test_sa_bool.py
test/test_sa_float.py
test/test_sa_int.py
test/test_sa_string.py
test/utils.py
pytsa-0.1.dist-info/METADATA
pytsa-0.1.dist-info/WHEEL
pytsa-0.1.dist-info/top_level.txt
pytsa-0.1.dist-info/RECORD
