Metadata-Version: 2.1
Name: pytsa
Version: 0.1
Summary: simple, human readable decorators package to ensure your method abides to it's contract
Home-page: https://github.com/thimovss/pytsa
Author: Thimo Visser
Author-email: thimo.visser@gmail.com
License: MIT
Project-URL: Source Code, https://github.com/thimovss/pytsa
Keywords: type strict arguments rules
Platform: UNKNOWN
Classifier: Programming Language :: Python :: 3 :: Only
Classifier: License :: OSI Approved :: MIT License
Classifier: Operating System :: OS Independent
Classifier: Topic :: Utilities
